{
  "schemaVersion": 1,
  "id": "jeffit-2021",
  "link": "https://sobakapav.ru/portfolio/jeffit-2021",
  "clientName": "Jeffit",
  "clientLogoFile": "",
  "preview": "",
  "title": "Система для юридических фирм и департаментов",
  "description": "",
  "createdAt": "2026-02-18T10:42:45.638Z",
  "updatedAt": "2026-02-19T10:32:39.785Z",
  "previewImageSourceUrl": "https://sobakapav.ru/images/portfolio/cards/jeffit.svg",
  "previewImageFile": "/case-previews/jeffit-2021.svg",
  "serviceIds": [
    "redesign",
    "ux-outsource"
  ],
  "year": 2021
}