{
  "schemaVersion": 1,
  "id": "pushkin-digital",
  "link": "https://sobakapav.ru/portfolio/pushkin-digital",
  "clientName": "",
  "clientLogoFile": "",
  "preview": "Создали интерфейсы научно-просветительского портала, где представлены рукописи и старые издания Пушкина, пушкинистика и справочные материалы.",
  "title": "Дизайн интерфейса коллекции материалов Пушкинского дома",
  "description": "",
  "createdAt": "2026-02-16T16:01:08.181Z",
  "updatedAt": "2026-02-17T12:40:17Z",
  "previewImageSourceUrl": "https://sobakapav.ru/_astro/itmo.X2OipU7q.svg",
  "previewImageFile": "/case-previews/pushkin-digital.svg"
}
