{
  "schemaVersion": 1,
  "id": "lab4u",
  "link": "https://sobakapav.ru/portfolio/lab4u",
  "clientName": "Lab4u",
  "clientLogoFile": "",
  "preview": "",
  "title": "Аудит сайта и приложения медицинской лаборатории",
  "description": "",
  "createdAt": "2026-02-16T16:01:08.180Z",
  "updatedAt": "2026-02-18T12:34:49.902Z",
  "previewImageSourceUrl": "https://sobakapav.ru/images/portfolio/cards/lab4u.svg",
  "previewImageFile": "/case-previews/lab4u.svg",
  "serviceIds": [
    "ux-audit"
  ],
  "year": 2025
}